odoo/addons/purchase_order_general_discount/README.rst
odoo/addons/purchase_order_general_discount/__init__.py
odoo/addons/purchase_order_general_discount/__manifest__.py
odoo/addons/purchase_order_general_discount/i18n/es.po
odoo/addons/purchase_order_general_discount/i18n/it.po
odoo/addons/purchase_order_general_discount/i18n/pt.po
odoo/addons/purchase_order_general_discount/i18n/pt_BR.po
odoo/addons/purchase_order_general_discount/i18n/purchase_order_general_discount.pot
odoo/addons/purchase_order_general_discount/models/__init__.py
odoo/addons/purchase_order_general_discount/models/purchase_order.py
odoo/addons/purchase_order_general_discount/models/res_company.py
odoo/addons/purchase_order_general_discount/models/res_config_settings.py
odoo/addons/purchase_order_general_discount/models/res_partner.py
odoo/addons/purchase_order_general_discount/readme/CONFIGURE.md
odoo/addons/purchase_order_general_discount/readme/CONTRIBUTORS.md
odoo/addons/purchase_order_general_discount/readme/DESCRIPTION.md
odoo/addons/purchase_order_general_discount/readme/USAGE.md
odoo/addons/purchase_order_general_discount/static/description/icon.png
odoo/addons/purchase_order_general_discount/static/description/index.html
odoo/addons/purchase_order_general_discount/tests/__init__.py
odoo/addons/purchase_order_general_discount/tests/test_purchase_order_general_discount.py
odoo/addons/purchase_order_general_discount/views/purchase_order_view.xml
odoo/addons/purchase_order_general_discount/views/res_config_view.xml
odoo/addons/purchase_order_general_discount/views/res_partner_view.xml
odoo_addon_purchase_order_general_discount-18.0.1.0.0.3.dist-info/METADATA
odoo_addon_purchase_order_general_discount-18.0.1.0.0.3.dist-info/WHEEL
odoo_addon_purchase_order_general_discount-18.0.1.0.0.3.dist-info/top_level.txt
odoo_addon_purchase_order_general_discount-18.0.1.0.0.3.dist-info/RECORD
